setup.py
neuq/__init__.py
neuq/server.py
neuq.egg-info/PKG-INFO
neuq.egg-info/SOURCES.txt
neuq.egg-info/dependency_links.txt
neuq.egg-info/entry_points.txt
neuq.egg-info/requires.txt
neuq.egg-info/top_level.txt